<?xml version="1.0" encoding="UTF-8"?>

<faces-config xmlns="http://java.sun.com/xml/ns/javaee"
	xmlns:xsi="http://www.w3.org/2001/XMLSchema-instance"
	xsi:schemaLocation="http://java.sun.com/xml/ns/javaee http://java.sun.com/xml/ns/javaee/web-facesconfig_2_0.xsd"
	version="2.0">
	<converter>
		<converter-id>selectItemObjectConverter</converter-id>
		<converter-class>bean.SelectItemObjectConvert</converter-class>
	</converter>

	<navigation-rule>
		<description>Login</description>
		<from-view-id>/loging.xhtml</from-view-id>
		<navigation-case>
			<from-outcome>correctoJefe</from-outcome>
			<to-view-id>/inicioJefe.xhtml</to-view-id>
		</navigation-case>
		<navigation-case>
			<from-outcome>incorrecto</from-outcome>
			<to-view-id>/loging.xhtml</to-view-id>
		</navigation-case>
		<navigation-case>
			<from-outcome>correctoSecretaria</from-outcome>
			<to-view-id>/inicioSecre.xhtml</to-view-id>
		</navigation-case>
		<navigation-case>
			<from-outcome>correctoAdmin</from-outcome>
			<to-view-id>/inicioAdmin.xhtml</to-view-id>
		</navigation-case>
		<navigation-case>
			<from-outcome>correctoAux</from-outcome>
			<to-view-id>/inicioWorker.xhtml</to-view-id>
		</navigation-case>
	</navigation-rule>

	<navigation-rule>
		<description>Registrar Comunicacion Secretaria</description>
		<from-view-id>/crearComS.xhtml</from-view-id>
		<navigation-case>
			<from-outcome>correctoCom</from-outcome>
			<to-view-id>/inicioSecre.xhtml</to-view-id>
		</navigation-case>
		<navigation-case>
			<from-outcome>cerrar</from-outcome>
			<to-view-id>/loging.xhtml</to-view-id>
		</navigation-case>
	</navigation-rule>

	<navigation-rule>
		<description>Registrar Comunicacion Jefe</description>
		<from-view-id>/crearComJ.xhtml</from-view-id>
		<navigation-case>
			<from-outcome>correctoCom</from-outcome>
			<to-view-id>/inicioJefe.xhtml</to-view-id>
		</navigation-case>
		<navigation-case>
			<from-outcome>cerrar</from-outcome>
			<to-view-id>/loging.xhtml</to-view-id>
		</navigation-case>
	</navigation-rule>

	<navigation-rule>
		<description>Registrar Comunicacion Secretaria Erroneo</description>
		<from-view-id>/crearComS.xhtml</from-view-id>
		<navigation-case>
			<from-outcome>algoSalioMal</from-outcome>
			<to-view-id>/inicioSecre.xhtml</to-view-id>
		</navigation-case>
		<navigation-case>
			<from-outcome>cerrar</from-outcome>
			<to-view-id>/loging.xhtml</to-view-id>
		</navigation-case>
	</navigation-rule>

	<navigation-rule>
		<from-view-id>/crearComS1.xhtml</from-view-id>
		<navigation-case>
			<from-outcome>algoSalioMal</from-outcome>
			<to-view-id>/crearComS1.xhtml</to-view-id>
		</navigation-case>
		<navigation-case>
			<from-outcome>correctoCom1</from-outcome>
			<to-view-id>/inicioSecre.xhtml</to-view-id>
		</navigation-case>
		<navigation-case>
			<from-outcome>comunicacionAprobada</from-outcome>
			<to-view-id>/inicioSecre.xhtml</to-view-id>
		</navigation-case>
		<navigation-case>
			<from-outcome>cerrar</from-outcome>
			<to-view-id>/loging.xhtml</to-view-id>
		</navigation-case>
	</navigation-rule>

	<navigation-rule>
		<description>Registrar Comunicacion Jefe Erroneo</description>
		<from-view-id>/crearComJ.xhtml</from-view-id>
		<navigation-case>
			<from-outcome>algoSalioMal</from-outcome>
			<to-view-id>/inicioJefe.xhtml</to-view-id>
		</navigation-case>
		<navigation-case>
			<from-outcome>cerrar</from-outcome>
			<to-view-id>/loging.xhtml</to-view-id>
		</navigation-case>
	</navigation-rule>

	<navigation-rule>
		<from-view-id>/crearComJ1.xhtml</from-view-id>
		<navigation-case>
			<from-outcome>algoSalioMal</from-outcome>
			<to-view-id>/crearComJ1.xhtml</to-view-id>
		</navigation-case>
		<navigation-case>
			<from-outcome>correctoCom1</from-outcome>
			<to-view-id>/inicioJefe.xhtml</to-view-id>
		</navigation-case>
		<navigation-case>
			<from-outcome>correctoECom1</from-outcome>
			<to-view-id>/inicioJefe.xhtml</to-view-id>
		</navigation-case>
		<navigation-case>
			<from-outcome>comunicacionAprobada</from-outcome>
			<to-view-id>/inicioJefe.xhtml</to-view-id>
		</navigation-case>
		<navigation-case>
			<from-outcome>cerrar</from-outcome>
			<to-view-id>/loging.xhtml</to-view-id>
		</navigation-case>
	</navigation-rule>

	<navigation-rule>
		<description>Cerrar Sesion Secre</description>
		<from-view-id>/inicioSecre.xhtml</from-view-id>
		<navigation-case>
			<from-outcome>cerrar</from-outcome>
			<to-view-id>/loging.xhtml</to-view-id>
		</navigation-case>
		<navigation-case>
			<from-outcome>busqueda</from-outcome>
			<to-view-id>/resultadoBusquedaS.xhtml</to-view-id>
		</navigation-case>
	</navigation-rule>

	<navigation-rule>
		<from-view-id>/inicioWorker.xhtml</from-view-id>
		<navigation-case>
			<from-outcome>cerrar</from-outcome>
			<to-view-id>/loging.xhtml</to-view-id>
		</navigation-case>
		<navigation-case>
			<from-outcome>busqueda</from-outcome>
			<to-view-id>/resultadoBusquedaP.xhtml</to-view-id>
		</navigation-case>
	</navigation-rule>

	<navigation-rule>
		<from-view-id>/inicioWorkerBSalida.xhtml</from-view-id>
		<navigation-case>
			<from-outcome>cerrar</from-outcome>
			<to-view-id>/loging.xhtml</to-view-id>
		</navigation-case>
		<navigation-case>
			<from-outcome>busqueda</from-outcome>
			<to-view-id>/resultadoBusquedaP.xhtml</to-view-id>
		</navigation-case>
	</navigation-rule>

	<navigation-rule>
		<from-view-id>/inicioSecreBRegistrados.xhtml</from-view-id>
		<navigation-case>
			<from-outcome>cerrar</from-outcome>
			<to-view-id>/loging.xhtml</to-view-id>
		</navigation-case>
		<navigation-case>
			<from-outcome>busqueda</from-outcome>
			<to-view-id>/resultadoBusquedaS.xhtml</to-view-id>
		</navigation-case>
	</navigation-rule>

	<navigation-rule>
		<from-view-id>/inicioSecreBConstruccion.xhtml</from-view-id>
		<navigation-case>
			<from-outcome>cerrar</from-outcome>
			<to-view-id>/loging.xhtml</to-view-id>
		</navigation-case>
		<navigation-case>
			<from-outcome>busqueda</from-outcome>
			<to-view-id>/resultadoBusquedaS.xhtml</to-view-id>
		</navigation-case>
	</navigation-rule>

	<navigation-rule>
		<from-view-id>/inicioSecreBElaborados.xhtml</from-view-id>
		<navigation-case>
			<from-outcome>cerrar</from-outcome>
			<to-view-id>/loging.xhtml</to-view-id>
		</navigation-case>
		<navigation-case>
			<from-outcome>busqueda</from-outcome>
			<to-view-id>/resultadoBusquedaS.xhtml</to-view-id>
		</navigation-case>
	</navigation-rule>

	<navigation-rule>
		<from-view-id>/inicioSecreBRedactados.xhtml</from-view-id>
		<navigation-case>
			<from-outcome>cerrar</from-outcome>
			<to-view-id>/loging.xhtml</to-view-id>
		</navigation-case>
		<navigation-case>
			<from-outcome>busqueda</from-outcome>
			<to-view-id>/resultadoBusquedaS.xhtml</to-view-id>
		</navigation-case>
	</navigation-rule>

	<navigation-rule>
		<from-view-id>/inicioSecreBAprobados.xhtml</from-view-id>
		<navigation-case>
			<from-outcome>cerrar</from-outcome>
			<to-view-id>/loging.xhtml</to-view-id>
		</navigation-case>
		<navigation-case>
			<from-outcome>busqueda</from-outcome>
			<to-view-id>/resultadoBusquedaS.xhtml</to-view-id>
		</navigation-case>
	</navigation-rule>

	<navigation-rule>
		<from-view-id>/adminCrearContacto.xhtml</from-view-id>
		<navigation-case>
			<from-outcome>cerrar</from-outcome>
			<to-view-id>/loging.xhtml</to-view-id>
		</navigation-case>
	</navigation-rule>

	<navigation-rule>
		<from-view-id>/inicioSecreBSalida.xhtml</from-view-id>
		<navigation-case>
			<from-outcome>cerrar</from-outcome>
			<to-view-id>/loging.xhtml</to-view-id>
		</navigation-case>
		<navigation-case>
			<from-outcome>busqueda</from-outcome>
			<to-view-id>/resultadoBusquedaS.xhtml</to-view-id>
		</navigation-case>
	</navigation-rule>

	<navigation-rule>
		<description>Cerrar Sesion Admin</description>
		<from-view-id>/inicioAdmin.xhtml</from-view-id>
		<navigation-case>
			<from-outcome>cerrar</from-outcome>
			<to-view-id>/loging.xhtml</to-view-id>
		</navigation-case>
	</navigation-rule>

	<navigation-rule>
		<from-view-id>/adminActualizarPersona.xhtml</from-view-id>
		<navigation-case>
			<from-outcome>cerrar</from-outcome>
			<to-view-id>/loging.xhtml</to-view-id>
		</navigation-case>
	</navigation-rule>

	<navigation-rule>
		<from-view-id>/inicioJefe.xhtml</from-view-id>
		<navigation-case>
			<from-outcome>cerrar</from-outcome>
			<to-view-id>/loging.xhtml</to-view-id>
		</navigation-case>
		<navigation-case>
			<from-outcome>busqueda</from-outcome>
			<to-view-id>/resultadoBusqueda.xhtml</to-view-id>
		</navigation-case>
	</navigation-rule>

	<navigation-rule>
		<from-view-id>/inicioJefeBSalida.xhtml</from-view-id>
		<navigation-case>
			<from-outcome>cerrar</from-outcome>
			<to-view-id>/loging.xhtml</to-view-id>
		</navigation-case>
		<navigation-case>
			<from-outcome>busqueda</from-outcome>
			<to-view-id>/resultadoBusqueda.xhtml</to-view-id>
		</navigation-case>
	</navigation-rule>

	<navigation-rule>
		<from-view-id>/inicioJefeBRegistrados.xhtml</from-view-id>
		<navigation-case>
			<from-outcome>cerrar</from-outcome>
			<to-view-id>/loging.xhtml</to-view-id>
		</navigation-case>
		<navigation-case>
			<from-outcome>busqueda</from-outcome>
			<to-view-id>/resultadoBusqueda.xhtml</to-view-id>
		</navigation-case>
	</navigation-rule>

	<navigation-rule>
		<from-view-id>/inicioJefeBConstruccion.xhtml</from-view-id>
		<navigation-case>
			<from-outcome>cerrar</from-outcome>
			<to-view-id>/loging.xhtml</to-view-id>
		</navigation-case>
		<navigation-case>
			<from-outcome>busqueda</from-outcome>
			<to-view-id>/resultadoBusqueda.xhtml</to-view-id>
		</navigation-case>
	</navigation-rule>

	<navigation-rule>
		<from-view-id>/inicioJefeBElaborados.xhtml</from-view-id>
		<navigation-case>
			<from-outcome>cerrar</from-outcome>
			<to-view-id>/loging.xhtml</to-view-id>
		</navigation-case>
		<navigation-case>
			<from-outcome>busqueda</from-outcome>
			<to-view-id>/resultadoBusqueda.xhtml</to-view-id>
		</navigation-case>
	</navigation-rule>

	<navigation-rule>
		<from-view-id>/inicioJefeBRedactados.xhtml</from-view-id>
		<navigation-case>
			<from-outcome>cerrar</from-outcome>
			<to-view-id>/loging.xhtml</to-view-id>
		</navigation-case>
		<navigation-case>
			<from-outcome>busqueda</from-outcome>
			<to-view-id>/resultadoBusqueda.xhtml</to-view-id>
		</navigation-case>
	</navigation-rule>

	<navigation-rule>
		<from-view-id>/inicioJefeBAprobados.xhtml</from-view-id>
		<navigation-case>
			<from-outcome>cerrar</from-outcome>
			<to-view-id>/loging.xhtml</to-view-id>
		</navigation-case>
		<navigation-case>
			<from-outcome>busqueda</from-outcome>
			<to-view-id>/resultadoBusqueda.xhtml</to-view-id>
		</navigation-case>
	</navigation-rule>

	<navigation-rule>
		<from-view-id>/adminCrearContacto.xhtml</from-view-id>
		<navigation-case>
			<from-outcome>crearContacto</from-outcome>
			<to-view-id>/inicioAdmin.xhtml</to-view-id>
		</navigation-case>
		<navigation-case>
			<from-outcome>cerrar</from-outcome>
			<to-view-id>/loging.xhtml</to-view-id>
		</navigation-case>
	</navigation-rule>

	<navigation-rule>
		<from-view-id>/adminCrearRoles.xhtml</from-view-id>
		<navigation-case>
			<from-outcome>crearRol</from-outcome>
			<to-view-id>/inicioAdmin.xhtml</to-view-id>
		</navigation-case>
		<navigation-case>
			<from-outcome>cerrar</from-outcome>
			<to-view-id>/loging.xhtml</to-view-id>
		</navigation-case>
	</navigation-rule>

	<navigation-rule>
		<description>Leer comunicacion secre</description>
		<from-view-id>/inicioSecre.xhtml</from-view-id>
		<navigation-case>
			<from-outcome>leerComSecretaria</from-outcome>
			<to-view-id>/leerComS.xhtml</to-view-id>
		</navigation-case>
		<navigation-case>
			<from-outcome>cerrar</from-outcome>
			<to-view-id>/loging.xhtml</to-view-id>
		</navigation-case>
	</navigation-rule>

	<navigation-rule>
		<description>Olvido Contrasenia</description>
		<from-view-id>/olvidoContrasenia.xhtml</from-view-id>
		<navigation-case>
			<from-outcome>olvidoContrasenia</from-outcome>
			<to-view-id>/loging.xhtml</to-view-id>
		</navigation-case>
	</navigation-rule>

	<navigation-rule>
		<from-view-id>/crearMensaje.xhtml</from-view-id>
		<navigation-case>
			<from-outcome>mensajeEnviado</from-outcome>
			<to-view-id>/inicioJefe.xhtml</to-view-id>
		</navigation-case>
		<navigation-case>
			<from-outcome>algoSalioMal</from-outcome>
			<to-view-id>/crearMensaje.xhtml</to-view-id>
		</navigation-case>
		<navigation-case>
			<from-outcome>cerrar</from-outcome>
			<to-view-id>/loging.xhtml</to-view-id>
		</navigation-case>
	</navigation-rule>

	<navigation-rule>
		<description>Mensaje Secre</description>
		<from-view-id>/crearMensajeS.xhtml</from-view-id>
		<navigation-case>
			<from-outcome>mensajeEnviado</from-outcome>
			<to-view-id>/inicioSecre.xhtml</to-view-id>
		</navigation-case>
		<navigation-case>
			<from-outcome>algoSalioMal</from-outcome>
			<to-view-id>/crearMensajeS.xhtml</to-view-id>
		</navigation-case>
		<navigation-case>
			<from-outcome>cerrar</from-outcome>
			<to-view-id>/loging.xhtml</to-view-id>
		</navigation-case>
	</navigation-rule>

	<navigation-rule>
		<from-view-id>/crearMensajeP.xhtml</from-view-id>
		<navigation-case>
			<from-outcome>mensajeEnviado</from-outcome>
			<to-view-id>/inicioWorker.xhtml</to-view-id>
		</navigation-case>
		<navigation-case>
			<from-outcome>algoSalioMal</from-outcome>
			<to-view-id>/crearMensajeP.xhtml</to-view-id>
		</navigation-case>
		<navigation-case>
			<from-outcome>cerrar</from-outcome>
			<to-view-id>/loging.xhtml</to-view-id>
		</navigation-case>
	</navigation-rule>


	<navigation-rule>
		<description>Mensaje Jefe Respuesta</description>
		<from-view-id>/responderMensaje.xhtml</from-view-id>
		<navigation-case>
			<from-outcome>respuestaMensaje</from-outcome>
			<to-view-id>/inicioJefe.xhtml</to-view-id>
		</navigation-case>
		<navigation-case>
			<from-outcome>algoSalioMal</from-outcome>
			<to-view-id>/responderMensaje.xhtml</to-view-id>
		</navigation-case>
		<navigation-case>
			<from-outcome>cerrar</from-outcome>
			<to-view-id>/loging.xhtml</to-view-id>
		</navigation-case>
	</navigation-rule>

	<navigation-rule>
		<description>Mensaje Secre Respuesta</description>
		<from-view-id>/responderMensajeS.xhtml</from-view-id>
		<navigation-case>
			<from-outcome>respuestaMensaje</from-outcome>
			<to-view-id>/inicioSecre.xhtml</to-view-id>
		</navigation-case>
		<navigation-case>
			<from-outcome>algoSalioMal</from-outcome>
			<to-view-id>/responderMensajeS.xhtml</to-view-id>
		</navigation-case>
		<navigation-case>
			<from-outcome>cerrar</from-outcome>
			<to-view-id>/loging.xhtml</to-view-id>
		</navigation-case>
	</navigation-rule>

	<navigation-rule>
		<description>Mensaje Worker Respuesta</description>
		<from-view-id>/responderMensajeP.xhtml</from-view-id>
		<navigation-case>
			<from-outcome>respuestaMensaje</from-outcome>
			<to-view-id>/inicioWorker.xhtml</to-view-id>
		</navigation-case>
		<navigation-case>
			<from-outcome>algoSalioMal</from-outcome>
			<to-view-id>/responderMensajeP.xhtml</to-view-id>
		</navigation-case>
		<navigation-case>
			<from-outcome>cerrar</from-outcome>
			<to-view-id>/loging.xhtml</to-view-id>
		</navigation-case>
	</navigation-rule>

	<navigation-rule>
		<from-view-id>/edicionJ.xhtml</from-view-id>
		<navigation-case>
			<from-outcome>elaboracionGuardada</from-outcome>
			<to-view-id>/inicioJefe.xhtml</to-view-id>
		</navigation-case>
		<navigation-case>
			<from-outcome>comunicacionEnviada</from-outcome>
			<to-view-id>/inicioJefe.xhtml</to-view-id>
		</navigation-case>
		<navigation-case>
			<from-outcome>algoSalioMal</from-outcome>
			<to-view-id>/edicionJ.xhtml</to-view-id>
		</navigation-case>
		<navigation-case>
			<from-outcome>cerrar</from-outcome>
			<to-view-id>/loging.xhtml</to-view-id>
		</navigation-case>
	</navigation-rule>

	<navigation-rule>
		<from-view-id>/edicionJ1.xhtml</from-view-id>
		<navigation-case>
			<from-outcome>elaboracionGuardada</from-outcome>
			<to-view-id>/inicioJefe.xhtml</to-view-id>
		</navigation-case>
		<navigation-case>
			<from-outcome>enviarComunicacion</from-outcome>
			<to-view-id>/inicioJefe.xhtml</to-view-id>
		</navigation-case>
		<navigation-case>
			<from-outcome>algoSalioMal</from-outcome>
			<to-view-id>/edicionJ1.xhtml</to-view-id>
		</navigation-case>
		<navigation-case>
			<from-outcome>correctoECom1</from-outcome>
			<to-view-id>/inicioJefe.xhtml</to-view-id>
		</navigation-case>
		<navigation-case>
			<from-outcome>actualizacionGuardada</from-outcome>
			<to-view-id>/inicioJefe.xhtml</to-view-id>
		</navigation-case>
		<navigation-case>
			<from-outcome>cerrar</from-outcome>
			<to-view-id>/loging.xhtml</to-view-id>
		</navigation-case>
	</navigation-rule>

	<navigation-rule>
		<from-view-id>/construirComunicacion.xhtml</from-view-id>
		<navigation-case>
			<from-outcome>construccionAprobada</from-outcome>
			<to-view-id>/inicioJefe.xhtml</to-view-id>
		</navigation-case>
		<navigation-case>
			<from-outcome>construccionRechazada</from-outcome>
			<to-view-id>/inicioJefe.xhtml</to-view-id>
		</navigation-case>
		<navigation-case>
			<from-outcome>algoSalioMal</from-outcome>
			<to-view-id>/construirComunicacion.xhtml</to-view-id>
		</navigation-case>
		<navigation-case>
			<from-outcome>comunicacionEnviada</from-outcome>
			<to-view-id>/inicioJefe.xhtml</to-view-id>
		</navigation-case>
		<navigation-case>
			<from-outcome>cerrar</from-outcome>
			<to-view-id>/loging.xhtml</to-view-id>
		</navigation-case>
	</navigation-rule>

	<navigation-rule>
		<from-view-id>/construirComunicacionJ.xhtml</from-view-id>
		<navigation-case>
			<from-outcome>redaccionGuardada</from-outcome>
			<to-view-id>/inicioJefe.xhtml</to-view-id>
		</navigation-case>
		<navigation-case>
			<from-outcome>comunicacionEnviada</from-outcome>
			<to-view-id>/inicioJefe.xhtml</to-view-id>
		</navigation-case>
		<navigation-case>
			<from-outcome>algoSalioMal</from-outcome>
			<to-view-id>/construirComunicacionJ.xhtml</to-view-id>
		</navigation-case>
		<navigation-case>
			<from-outcome>cerrar</from-outcome>
			<to-view-id>/loging.xhtml</to-view-id>
		</navigation-case>
	</navigation-rule>

	<navigation-rule>
		<from-view-id>/construirCom1.xhtml</from-view-id>

		<navigation-case>
			<from-outcome>construccionAprobada</from-outcome>
			<to-view-id>/inicioJefe.xhtml</to-view-id>
		</navigation-case>
		<navigation-case>
			<from-outcome>algoSalioMal</from-outcome>
			<to-view-id>/construirCom1.xhtml</to-view-id>
		</navigation-case>
		<navigation-case>
			<from-outcome>comunicacionEnviada</from-outcome>
			<to-view-id>/inicioJefe.xhtml</to-view-id>
		</navigation-case>
		<navigation-case>
			<from-outcome>cerrar</from-outcome>
			<to-view-id>/loging.xhtml</to-view-id>
		</navigation-case>
	</navigation-rule>

	<navigation-rule>
		<from-view-id>/construirCom1S.xhtml</from-view-id>
		<navigation-case>
			<from-outcome>construccionAprobada</from-outcome>
			<to-view-id>/inicioSecre.xhtml</to-view-id>
		</navigation-case>
		<navigation-case>
			<from-outcome>comunicacionEnviada</from-outcome>
			<to-view-id>/inicioSecre.xhtml</to-view-id>
		</navigation-case>
		<navigation-case>
			<from-outcome>algoSalioMal</from-outcome>
			<to-view-id>/construirCom1S.xhtml</to-view-id>
		</navigation-case>
		<navigation-case>
			<from-outcome>cerrar</from-outcome>
			<to-view-id>/loging.xhtml</to-view-id>
		</navigation-case>
	</navigation-rule>

	<navigation-rule>
		<from-view-id>/construirComunicacionS.xhtml</from-view-id>
		<navigation-case>
			<from-outcome>construccionGuardada</from-outcome>
			<to-view-id>/inicioSecre.xhtml</to-view-id>
		</navigation-case>
		<navigation-case>
			<from-outcome>algoSalioMal</from-outcome>
			<to-view-id>/construirComunicacionS.xhtml</to-view-id>
		</navigation-case>
		<navigation-case>
			<from-outcome>cerrar</from-outcome>
			<to-view-id>/loging.xhtml</to-view-id>
		</navigation-case>
	</navigation-rule>

	<navigation-rule>
		<from-view-id>/redactarComunicacion.xhtml</from-view-id>
		<navigation-case>
			<from-outcome>redaccionAprobada</from-outcome>
			<to-view-id>/inicioJefe.xhtml</to-view-id>
		</navigation-case>
		<navigation-case>
			<from-outcome>redaccionRechazada</from-outcome>
			<to-view-id>/inicioJefe.xhtml</to-view-id>
		</navigation-case>
		<navigation-case>
			<from-outcome>algoSalioMal</from-outcome>
			<to-view-id>/redactarComunicacion.xhtml</to-view-id>
		</navigation-case>
		<navigation-case>
			<from-outcome>comunicacionEnviada</from-outcome>
			<to-view-id>/inicioJefe.xhtml</to-view-id>
		</navigation-case>
		<navigation-case>
			<from-outcome>cerrar</from-outcome>
			<to-view-id>/loging.xhtml</to-view-id>
		</navigation-case>
	</navigation-rule>

	<navigation-rule>
		<from-view-id>/redactarCom1.xhtml</from-view-id>
		<navigation-case>
			<from-outcome>redaccionGuardada</from-outcome>
			<to-view-id>/inicioJefe.xhtml</to-view-id>
		</navigation-case>
		<navigation-case>
			<from-outcome>algoSalioMal</from-outcome>
			<to-view-id>/redactarCom1.xhtml</to-view-id>
		</navigation-case>
		<navigation-case>
			<from-outcome>comunicacionEnviada</from-outcome>
			<to-view-id>/inicioJefe.xhtml</to-view-id>
		</navigation-case>
		<navigation-case>
			<from-outcome>cerrar</from-outcome>
			<to-view-id>/loging.xhtml</to-view-id>
		</navigation-case>
	</navigation-rule>

	<navigation-rule>
		<from-view-id>/redactarCom1S.xhtml</from-view-id>
		<navigation-case>
			<from-outcome>redaccionGuardada</from-outcome>
			<to-view-id>/inicioSecre.xhtml</to-view-id>
		</navigation-case>
		<navigation-case>
			<from-outcome>comunicacionAprobada</from-outcome>
			<to-view-id>/inicioSecre.xhtml</to-view-id>
		</navigation-case>
		<navigation-case>
			<from-outcome>algoSalioMal</from-outcome>
			<to-view-id>/redactarCom1S.xhtml</to-view-id>
		</navigation-case>
		<navigation-case>
			<from-outcome>comunicacionEnviada</from-outcome>
			<to-view-id>/inicioSecre.xhtml</to-view-id>
		</navigation-case>
		<navigation-case>
			<from-outcome>cerrar</from-outcome>
			<to-view-id>/loging.xhtml</to-view-id>
		</navigation-case>
	</navigation-rule>

	<navigation-rule>
		<from-view-id>/aprobarComunicacion.xhtml</from-view-id>
		<navigation-case>
			<from-outcome>comunicacionAprobada</from-outcome>
			<to-view-id>/inicioJefe.xhtml</to-view-id>
		</navigation-case>
		<navigation-case>
			<from-outcome>algoSalioMal</from-outcome>
			<to-view-id>/aprobarComunicacion.xhtml</to-view-id>
		</navigation-case>
		<navigation-case>
			<from-outcome>cerrar</from-outcome>
			<to-view-id>/loging.xhtml</to-view-id>
		</navigation-case>
	</navigation-rule>

	<navigation-rule>
		<from-view-id>/redactarComunicacionS.xhtml</from-view-id>
		<navigation-case>
			<from-outcome>redaccionGuardada</from-outcome>
			<to-view-id>/inicioSecre.xhtml</to-view-id>
		</navigation-case>
		<navigation-case>
			<from-outcome>algoSalioMal</from-outcome>
			<to-view-id>/redactarComunicacionS.xhtml</to-view-id>
		</navigation-case>
		<navigation-case>
			<from-outcome>cerrar</from-outcome>
			<to-view-id>/loging.xhtml</to-view-id>
		</navigation-case>
	</navigation-rule>

	<navigation-rule>
		<from-view-id>/edicionSecre.xhtml</from-view-id>
		<navigation-case>
			<from-outcome>elaboracionGuardada</from-outcome>
			<to-view-id>/inicioSecre.xhtml</to-view-id>
		</navigation-case>
		<navigation-case>
			<from-outcome>algoSalioMal</from-outcome>
			<to-view-id>/edicionSecre.xhtml</to-view-id>
		</navigation-case>
		<navigation-case>
			<from-outcome>cerrar</from-outcome>
			<to-view-id>/loging.xhtml</to-view-id>
		</navigation-case>
	</navigation-rule>

	<navigation-rule>
		<from-view-id>/edicionSecre1.xhtml</from-view-id>
		<navigation-case>
			<from-outcome>comunicacionAprobada</from-outcome>
			<to-view-id>/inicioSecre.xhtml</to-view-id>
		</navigation-case>
		<navigation-case>
			<from-outcome>comunicacionEnviada</from-outcome>
			<to-view-id>/inicioSecre.xhtml</to-view-id>
		</navigation-case>
		<navigation-case>
			<from-outcome>algoSalioMal</from-outcome>
			<to-view-id>/edicionSecre1.xhtml</to-view-id>
		</navigation-case>
		<navigation-case>
			<from-outcome>elaboracionGuardada</from-outcome>
			<to-view-id>/inicioSecre.xhtml</to-view-id>
		</navigation-case>
		<navigation-case>
			<from-outcome>cerrar</from-outcome>
			<to-view-id>/loging.xhtml</to-view-id>
		</navigation-case>
	</navigation-rule>

	<navigation-rule>
		<from-view-id>/resultadoBusqueda.xhtml</from-view-id>
		<navigation-case>
			<from-outcome>cerrar</from-outcome>
			<to-view-id>/loging.xhtml</to-view-id>
		</navigation-case>
		<navigation-case>
			<from-outcome>busqueda</from-outcome>
			<to-view-id>/resultadoBusqueda.xhtml</to-view-id>
		</navigation-case>
	</navigation-rule>

	<navigation-rule>
		<from-view-id>/resultadoBusquedaS.xhtml</from-view-id>
		<navigation-case>
			<from-outcome>busqueda</from-outcome>
			<to-view-id>/resultadoBusquedaS.xhtml</to-view-id>
		</navigation-case>
		<navigation-case>
			<from-outcome>cerrar</from-outcome>
			<to-view-id>/loging.xhtml</to-view-id>
		</navigation-case>
	</navigation-rule>

	<navigation-rule>
		<from-view-id>/resultadoBusquedaP.xhtml</from-view-id>
		<navigation-case>
			<from-outcome>busqueda</from-outcome>
			<to-view-id>/resultadoBusquedaP.xhtml</to-view-id>
		</navigation-case>
		<navigation-case>
			<from-outcome>cerrar</from-outcome>
			<to-view-id>/loging.xhtml</to-view-id>
		</navigation-case>
	</navigation-rule>

	<navigation-rule>
		<from-view-id>/camPW.xhtml</from-view-id>
		<navigation-case>
			<from-outcome>cambioPass</from-outcome>
			<to-view-id>/inicioJefe.xhtml</to-view-id>
		</navigation-case>
		<navigation-case>
			<from-outcome>cerrar</from-outcome>
			<to-view-id>/loging.xhtml</to-view-id>
		</navigation-case>
	</navigation-rule>

	<navigation-rule>
		<from-view-id>/camPWS.xhtml</from-view-id>
		<navigation-case>
			<from-outcome>cambioPass</from-outcome>
			<to-view-id>/inicioSecre.xhtml</to-view-id>
		</navigation-case>
		<navigation-case>
			<from-outcome>cerrar</from-outcome>
			<to-view-id>/loging.xhtml</to-view-id>
		</navigation-case>
	</navigation-rule>

	<navigation-rule>
		<from-view-id>/leerComJ.xhtml</from-view-id>
		<navigation-case>
			<from-outcome>cerrar</from-outcome>
			<to-view-id>/loging.xhtml</to-view-id>
		</navigation-case>
		<navigation-case>
			<from-outcome>busqueda</from-outcome>
			<to-view-id>/resultadoBusqueda.xhtml</to-view-id>
		</navigation-case>
	</navigation-rule>

	<navigation-rule>
		<from-view-id>/leerComS.xhtml</from-view-id>
		<navigation-case>
			<from-outcome>cerrar</from-outcome>
			<to-view-id>/loging.xhtml</to-view-id>
		</navigation-case>
		<navigation-case>
			<from-outcome>busqueda</from-outcome>
			<to-view-id>/resultadoBusquedaS.xhtml</to-view-id>
		</navigation-case>
	</navigation-rule>

	<navigation-rule>
		<from-view-id>/leerComP.xhtml</from-view-id>
		<navigation-case>
			<from-outcome>cerrar</from-outcome>
			<to-view-id>/loging.xhtml</to-view-id>
		</navigation-case>
		<navigation-case>
			<from-outcome>busqueda</from-outcome>
			<to-view-id>/resultadoBusquedaP.xhtml</to-view-id>
		</navigation-case>
	</navigation-rule>

	<navigation-rule>
		<from-view-id>/leerConversacion.xhtml</from-view-id>
		<navigation-case>
			<from-outcome>cerrar</from-outcome>
			<to-view-id>/loging.xhtml</to-view-id>
		</navigation-case>
		<navigation-case>
			<from-outcome>busqueda</from-outcome>
			<to-view-id>/resultadoBusqueda.xhtml</to-view-id>
		</navigation-case>
	</navigation-rule>

	<navigation-rule>
		<from-view-id>/leerConversacionS.xhtml</from-view-id>
		<navigation-case>
			<from-outcome>cerrar</from-outcome>
			<to-view-id>/loging.xhtml</to-view-id>
		</navigation-case>
		<navigation-case>
			<from-outcome>busqueda</from-outcome>
			<to-view-id>/resultadoBusquedaS.xhtml</to-view-id>
		</navigation-case>
	</navigation-rule>

	<navigation-rule>
		<from-view-id>/leerConversacionP.xhtml</from-view-id>
		<navigation-case>
			<from-outcome>cerrar</from-outcome>
			<to-view-id>/loging.xhtml</to-view-id>
		</navigation-case>
		<navigation-case>
			<from-outcome>busqueda</from-outcome>
			<to-view-id>/resultadoBusquedaP.xhtml</to-view-id>
		</navigation-case>
	</navigation-rule>

	<navigation-rule>
		<from-view-id>/enviarComunicacionS.xhtml</from-view-id>
		<navigation-case>
			<from-outcome>cerrar</from-outcome>
			<to-view-id>/loging.xhtml</to-view-id>
		</navigation-case>
		<navigation-case>
			<from-outcome>busqueda</from-outcome>
			<to-view-id>/resultadoBusquedaS.xhtml</to-view-id>
		</navigation-case>
		<navigation-case>
			<from-outcome>algoSalioMal</from-outcome>
			<to-view-id>/enviarComunicacionS.xhtml</to-view-id>
		</navigation-case>
		<navigation-case>
			<from-outcome>comunicacionEnviada</from-outcome>
			<to-view-id>/inicioSecre.xhtml</to-view-id>
		</navigation-case>
	</navigation-rule>

	<navigation-rule>
		<from-view-id>/enviarComunicacion.xhtml</from-view-id>
		<navigation-case>
			<from-outcome>cerrar</from-outcome>
			<to-view-id>/loging.xhtml</to-view-id>
		</navigation-case>
		<navigation-case>
			<from-outcome>busqueda</from-outcome>
			<to-view-id>/resultadoBusqueda.xhtml</to-view-id>
		</navigation-case>
		<navigation-case>
			<from-outcome>algoSalioMal</from-outcome>
			<to-view-id>/enviarComunicacion.xhtml</to-view-id>
		</navigation-case>
		<navigation-case>
			<from-outcome>comunicacionEnviada</from-outcome>
			<to-view-id>/inicioJefe.xhtml</to-view-id>
		</navigation-case>
	</navigation-rule>

	<navigation-rule>
		<from-view-id>/elaborarComunicacion.xhtml</from-view-id>
		<navigation-case>
			<from-outcome>cerrar</from-outcome>
			<to-view-id>/loging.xhtml</to-view-id>
		</navigation-case>
		<navigation-case>
			<from-outcome>algoSalioMal</from-outcome>
			<to-view-id>/elaborarComunicacion.xhtml</to-view-id>
		</navigation-case>
		<navigation-case>
			<from-outcome>construccionGuardada</from-outcome>
			<to-view-id>/inicioJefe.xhtml</to-view-id>
		</navigation-case>
		<navigation-case>
			<from-outcome>comunicacionEnviada</from-outcome>
			<to-view-id>/inicioJefe.xhtml</to-view-id>
		</navigation-case>
	</navigation-rule>

	<navigation-rule>
		<from-view-id>/crearCircular.xhtml</from-view-id>
		<navigation-case>
			<from-outcome>cerrar</from-outcome>
			<to-view-id>/loging.xhtml</to-view-id>
		</navigation-case>
		<navigation-case>
			<from-outcome>correctoCom</from-outcome>
			<to-view-id>/inicioJefe.xhtml</to-view-id>
		</navigation-case>
		<navigation-case>
			<from-outcome>circularEnviada</from-outcome>
			<to-view-id>/inicioJefe.xhtml</to-view-id>
		</navigation-case>
		<navigation-case>
			<from-outcome>algoSalioMal</from-outcome>
			<to-view-id>/inicioJefe.xhtml</to-view-id>
		</navigation-case>
	</navigation-rule>

	<navigation-rule>
		<from-view-id>/crearCircularS.xhtml</from-view-id>
		<navigation-case>
			<from-outcome>cerrar</from-outcome>
			<to-view-id>/loging.xhtml</to-view-id>
		</navigation-case>
		<navigation-case>
			<from-outcome>correctoCom</from-outcome>
			<to-view-id>/inicioSecre.xhtml</to-view-id>
		</navigation-case>
		<navigation-case>
			<from-outcome>circularEnviada</from-outcome>
			<to-view-id>/inicioSecre.xhtml</to-view-id>
		</navigation-case>
		<navigation-case>
			<from-outcome>algoSalioMal</from-outcome>
			<to-view-id>/inicioSecre.xhtml</to-view-id>
		</navigation-case>
	</navigation-rule>

	<navigation-rule>
		<from-view-id>/crearComW.xhtml</from-view-id>
		<navigation-case>
			<from-outcome>cerrar</from-outcome>
			<to-view-id>/loging.xhtml</to-view-id>
		</navigation-case>
		<navigation-case>
			<from-outcome>comunicacionAprobada</from-outcome>
			<to-view-id>/inicioWorker.xhtml</to-view-id>
		</navigation-case>
		<navigation-case>
			<from-outcome>algoSalioMal</from-outcome>
			<to-view-id>/inicioWorker.xhtml</to-view-id>
		</navigation-case>
	</navigation-rule>

	<navigation-rule>
		<from-view-id>/leerConversacionComunicacion.xhtml</from-view-id>
		<navigation-case>
			<from-outcome>cerrar</from-outcome>
			<to-view-id>/loging.xhtml</to-view-id>
		</navigation-case>
	</navigation-rule>

	<navigation-rule>
		<from-view-id>/leerConversacionComunicacion1.xhtml</from-view-id>
		<navigation-case>
			<from-outcome>cerrar</from-outcome>
			<to-view-id>/loging.xhtml</to-view-id>
		</navigation-case>
	</navigation-rule>

	<navigation-rule>
		<from-view-id>/leerConversacionComunicacion1Construccion.xhtml</from-view-id>
		<navigation-case>
			<from-outcome>cerrar</from-outcome>
			<to-view-id>/loging.xhtml</to-view-id>
		</navigation-case>
	</navigation-rule>

	<navigation-rule>
		<from-view-id>/leerConversacionComunicacion1Elaboracion.xhtml</from-view-id>
		<navigation-case>
			<from-outcome>cerrar</from-outcome>
			<to-view-id>/loging.xhtml</to-view-id>
		</navigation-case>
	</navigation-rule>

	<navigation-rule>
		<from-view-id>/leerConversacionComunicacion1S.xhtml</from-view-id>
		<navigation-case>
			<from-outcome>cerrar</from-outcome>
			<to-view-id>/loging.xhtml</to-view-id>
		</navigation-case>
	</navigation-rule>

	<navigation-rule>
		<from-view-id>/leerConversacionComunicacion1SConstruccion.xhtml</from-view-id>
		<navigation-case>
			<from-outcome>cerrar</from-outcome>
			<to-view-id>/loging.xhtml</to-view-id>
		</navigation-case>
	</navigation-rule>

	<navigation-rule>
		<from-view-id>/leerConversacionComunicacion1SElaboracion.xhtml</from-view-id>
		<navigation-case>
			<from-outcome>cerrar</from-outcome>
			<to-view-id>/loging.xhtml</to-view-id>
		</navigation-case>
	</navigation-rule>

	<navigation-rule>
		<from-view-id>/leerConversacionComunicacionAprobada.xhtml</from-view-id>
		<navigation-case>
			<from-outcome>cerrar</from-outcome>
			<to-view-id>/loging.xhtml</to-view-id>
		</navigation-case>
	</navigation-rule>

	<navigation-rule>
		<from-view-id>/leerConversacionComunicacionConstruccion.xhtml</from-view-id>
		<navigation-case>
			<from-outcome>cerrar</from-outcome>
			<to-view-id>/loging.xhtml</to-view-id>
		</navigation-case>
	</navigation-rule>

	<navigation-rule>
		<from-view-id>/leerConversacionComunicacionElaboracion.xhtml</from-view-id>
		<navigation-case>
			<from-outcome>cerrar</from-outcome>
			<to-view-id>/loging.xhtml</to-view-id>
		</navigation-case>
	</navigation-rule>

	<navigation-rule>
		<from-view-id>/leerConversacionComunicacionElaboracionS.xhtml</from-view-id>
		<navigation-case>
			<from-outcome>cerrar</from-outcome>
			<to-view-id>/loging.xhtml</to-view-id>
		</navigation-case>
	</navigation-rule>

	<navigation-rule>
		<from-view-id>/leerConversacionComunicacionEnConstruccion.xhtml</from-view-id>
		<navigation-case>
			<from-outcome>cerrar</from-outcome>
			<to-view-id>/loging.xhtml</to-view-id>
		</navigation-case>
	</navigation-rule>

	<navigation-rule>
		<from-view-id>/leerConversacionComunicacionEnRedaccion.xhtml</from-view-id>
		<navigation-case>
			<from-outcome>cerrar</from-outcome>
			<to-view-id>/loging.xhtml</to-view-id>
		</navigation-case>
	</navigation-rule>

	<navigation-rule>
		<from-view-id>/leerConversacionComunicacionRedaccion.xhtml</from-view-id>
		<navigation-case>
			<from-outcome>cerrar</from-outcome>
			<to-view-id>/loging.xhtml</to-view-id>
		</navigation-case>
	</navigation-rule>

	<navigation-rule>
		<from-view-id>/leerConversacionComunicacionS.xhtml</from-view-id>
		<navigation-case>
			<from-outcome>cerrar</from-outcome>
			<to-view-id>/loging.xhtml</to-view-id>
		</navigation-case>
	</navigation-rule>

	<navigation-rule>
		<from-view-id>/leerConversacionComunicacionSAprobada.xhtml</from-view-id>
		<navigation-case>
			<from-outcome>cerrar</from-outcome>
			<to-view-id>/loging.xhtml</to-view-id>
		</navigation-case>
	</navigation-rule>

	<navigation-rule>
		<from-view-id>/leerConversacionComunicacionSConstruccion.xhtml</from-view-id>
		<navigation-case>
			<from-outcome>cerrar</from-outcome>
			<to-view-id>/loging.xhtml</to-view-id>
		</navigation-case>
	</navigation-rule>

	<navigation-rule>
		<from-view-id>/leerConversacionComunicacionSElaboracion.xhtml</from-view-id>
		<navigation-case>
			<from-outcome>cerrar</from-outcome>
			<to-view-id>/loging.xhtml</to-view-id>
		</navigation-case>
	</navigation-rule>

	<navigation-rule>
		<from-view-id>/leerConversacionComunicacionSEnConstruccion.xhtml</from-view-id>
		<navigation-case>
			<from-outcome>cerrar</from-outcome>
			<to-view-id>/loging.xhtml</to-view-id>
		</navigation-case>
	</navigation-rule>

	<navigation-rule>
		<from-view-id>/leerConversacionComunicacionSEnRedaccion.xhtml</from-view-id>
		<navigation-case>
			<from-outcome>cerrar</from-outcome>
			<to-view-id>/loging.xhtml</to-view-id>
		</navigation-case>
	</navigation-rule>

</faces-config>